fxitility/__init__.py
fxitility/fxitility.py
fxitility/main.py
fxitility/test.py
fxitily/__init__.py
fxitily/fxitily.py
fxitily/test.py
fxitility-0.0.3.dist-info/LICENSE
fxitility-0.0.3.dist-info/METADATA
fxitility-0.0.3.dist-info/WHEEL
fxitility-0.0.3.dist-info/top_level.txt
fxitility-0.0.3.dist-info/RECORD
