Metadata-Version: 2.1
Name: fxitility
Version: 0.0.3
Summary: Forex Utility Package
Home-page: https://github.com/jmawirat/fxitility
Author: Jonel Agustin Mawirat
Author-email: jmawirat@fivetalents.capital
Keywords: Forex
Classifier: Programming Language :: Python :: 3
Classifier: Operating System :: OS Independent
License-File: LICENSE
